tronald/__init__.py
tronald/__main__.py
tronald/cli.py
tronald/commands.py
tronald/config.py
tronald/controllers.py
tronald/initial.py
tronald-0.4.0.dist-info/entry_points.txt
tronald-0.4.0.dist-info/WHEEL
tronald-0.4.0.dist-info/METADATA
tronald-0.4.0.dist-info/RECORD
