Metadata-Version: 2.1
Name: tronald
Version: 0.4.0
Summary: CLI for getting Postgres dumps from remote containers.
Home-page: https://github.com/filipweidemann/tronald
Author: Filip Weidemann
Author-email: filip.weidemann@outlook.de
Requires-Python: >=3.6,<4.0
Classifier: Programming Language :: Python :: 3
Classifier: Programming Language :: Python :: 3.6
Classifier: Programming Language :: Python :: 3.7
Requires-Dist: click (>=7.0,<8.0)
Requires-Dist: inquirer (>=2.5,<3.0)
Requires-Dist: paramiko (>=2.4,<3.0)
